aiohttp_transmute/__init__.py
aiohttp_transmute/handler.py
aiohttp_transmute/route.py
aiohttp_transmute/swagger.py
aiohttp_transmute/url_dispatcher.py
aiohttp_transmute/tests/__init__.py
aiohttp_transmute/tests/conftest.py
aiohttp_transmute/tests/example.py
aiohttp_transmute/tests/test_full.py
aiohttp_transmute/tests/test_handler.py
aiohttp_transmute/tests/test_parsing.py
aiohttp_transmute/tests/test_urldispatcher.py
aiohttp_transmute/tests/utils.py
aiohttp_transmute-2.0.0.dist-info/LICENSE
aiohttp_transmute-2.0.0.dist-info/METADATA
aiohttp_transmute-2.0.0.dist-info/WHEEL
aiohttp_transmute-2.0.0.dist-info/top_level.txt
aiohttp_transmute-2.0.0.dist-info/RECORD
