Metadata-Version: 2.1
Name: aiohttp-transmute
Version: 2.0.0
Summary: a toolset to generate routes from functions for aiohttp.
Home-page: UNKNOWN
Author: Yusuke Tsutsumi
Author-email: yusuke@tsutsumi.io
License: UNKNOWN
Platform: UNKNOWN
Classifier: Development Status :: 5 - Production/Stable
Classifier: Operating System :: MacOS
Classifier: Operating System :: POSIX :: Linux
Classifier: Topic :: System :: Software Distribution
Classifier: License :: OSI Approved :: MIT License
Classifier: Programming Language :: Python
Classifier: Programming Language :: Python :: 3
Classifier: Programming Language :: Python :: 3.5
Requires-Dist: transmute-core (>=1.11.0)
Requires-Dist: aiohttp (>=2.3.8)
